CHANGELOG.md
openapi_python_client/__init__.py
openapi_python_client/__main__.py
openapi_python_client/cli.py
openapi_python_client/config.py
openapi_python_client/parser/__init__.py
openapi_python_client/parser/errors.py
openapi_python_client/parser/openapi.py
openapi_python_client/parser/properties/__init__.py
openapi_python_client/parser/properties/converter.py
openapi_python_client/parser/properties/enum_property.py
openapi_python_client/parser/properties/model_property.py
openapi_python_client/parser/properties/property.py
openapi_python_client/parser/properties/schemas.py
openapi_python_client/parser/responses.py
openapi_python_client/py.typed
openapi_python_client/schema/__init__.py
openapi_python_client/schema/data_type.py
openapi_python_client/schema/openapi_schema_pydantic/LICENSE
openapi_python_client/schema/openapi_schema_pydantic/README.md
openapi_python_client/schema/openapi_schema_pydantic/__init__.py
openapi_python_client/schema/openapi_schema_pydantic/callback.py
openapi_python_client/schema/openapi_schema_pydantic/components.py
openapi_python_client/schema/openapi_schema_pydantic/contact.py
openapi_python_client/schema/openapi_schema_pydantic/discriminator.py
openapi_python_client/schema/openapi_schema_pydantic/encoding.py
openapi_python_client/schema/openapi_schema_pydantic/example.py
openapi_python_client/schema/openapi_schema_pydantic/external_documentation.py
openapi_python_client/schema/openapi_schema_pydantic/header.py
openapi_python_client/schema/openapi_schema_pydantic/info.py
openapi_python_client/schema/openapi_schema_pydantic/license.py
openapi_python_client/schema/openapi_schema_pydantic/link.py
openapi_python_client/schema/openapi_schema_pydantic/media_type.py
openapi_python_client/schema/openapi_schema_pydantic/oauth_flow.py
openapi_python_client/schema/openapi_schema_pydantic/oauth_flows.py
openapi_python_client/schema/openapi_schema_pydantic/open_api.py
openapi_python_client/schema/openapi_schema_pydantic/operation.py
binarylane_python_client-0.13.1.dist-info/entry_points.txt
binarylane_python_client-0.13.1.dist-info/LICENSE
binarylane_python_client-0.13.1.dist-info/WHEEL
binarylane_python_client-0.13.1.dist-info/METADATA
binarylane_python_client-0.13.1.dist-info/RECORD
