Metadata-Version: 2.1
Name: binarylane-python-client
Version: 0.13.1
Summary: Generate modern Python clients from OpenAPI
Home-page: https://github.com/triaxtec/openapi-python-client
License: MIT
Keywords: OpenAPI,Client,Generator
Author: Dylan Anthony
Author-email: danthony@triaxtec.com
Requires-Python: >=3.7.2,<4.0.0
Classifier: Development Status :: 3 - Alpha
Classifier: Intended Audience :: Developers
Classifier: License :: OSI Approved :: MIT License
Classifier: Programming Language :: Python :: 3
Classifier: Programming Language :: Python :: 3.8
Classifier: Programming Language :: Python :: 3.9
Classifier: Programming Language :: Python :: 3.10
Classifier: Topic :: Software Development :: Code Generators
Classifier: Typing :: Typed
Requires-Dist: PyYAML (>=6.0,<7.0)
Requires-Dist: attrs (>=21.3.0)
Requires-Dist: autoflake (>=1.4,<3.0.0)
Requires-Dist: black
Requires-Dist: colorama (>=0.4.3,<0.5.0); sys_platform == "win32"
Requires-Dist: httpx (>=0.15.4,<0.24.0)
Requires-Dist: importlib_metadata (>2,<7); python_version < "3.8"
Requires-Dist: isort (>=5.0.5,<6.0.0)
Requires-Dist: jinja2 (>=3.0.0,<4.0.0)
Requires-Dist: pydantic (>=1.6.1,<2.0.0)
Requires-Dist: python-dateutil (>=2.8.1,<3.0.0)
Requires-Dist: shellingham (>=1.3.2,<2.0.0)
Requires-Dist: typer (>=0.6,<0.8.0)
Requires-Dist: typing-extensions; python_version < "3.8"
Project-URL: Repository, https://github.com/triaxtec/openapi-python-client
